{
  "controller/View1.controller.js": 1777292876280,
  "manifest.json": 1772702025038,
  "controller/View2.controller.js": 1772202284649,
  "i18n/i18n.properties": 1775801688214,
  "controller/App.controller.js": 1771918986841,
  "model/models.js": 1771918986837,
  "Component.js": 1774634864268,
  "Component-dbg.js": 1774634864268,
  "Component.js.map": 1777302535727,
  "controller/View1-dbg.controller.js": 1777292876280,
  "controller/View1.controller.js.map": 1777302536015,
  "controller/App-dbg.controller.js": 1771918986841,
  "controller/App.controller.js.map": 1777302535727,
  "model/models-dbg.js": 1771918986837,
  "model/models.js.map": 1777302535718,
  "controller/View2-dbg.controller.js": 1772202284649,
  "controller/View2.controller.js.map": 1777302535738,
  "Component-preload.js": 1777302536309,
  "Component-preload.js.map": 1777302536310,
  "view/View2.view.xml": 1772427564427,
  "view/View1.view.xml": 1777302488648,
  "view/App.view.xml": 1771918986845,
  "css/style.css": 1775751221096,
  "index.html": 1777033035875
}